{"11111":[{"empId":11111,"beve":"orange","qty":3,"date":"2019-11-27T11:40:37.464Z"},{"empId":11111,"beve":"orange","qty":3,"date":"2019-11-28T06:15:39.604Z"},{"empId":11111,"beve":"orange","qty":3,"date":"2019-11-28T06:20:59.320Z"}],"11112":[{"empId":11112,"beve":"orange","qty":3,"date":"2019-11-27T11:40:45.585Z"},{"empId":11112,"beve":"banana","qty":3,"date":"2019-11-27T11:41:45.293Z"}],"11115":[{"empId":11115,"beve":"banana","qty":3,"date":"2019-11-27T11:42:14.094Z"},{"empId":11115,"beve":"banana","qty":2,"date":"2019-11-27T11:42:24.669Z"}]}